verahession/__init__.py
verahession/api/__init__.py
verahession/api/client.py
verahession/api/tts.py
verahession/assistant/__init__.py
verahession/assistant/classifier.py
verahession/assistant/export_to_numpy.py
verahession/assistant/model.py
verahession/assistant/train.py
verahession/assistant/utils.py
verahession-0.1.28.dist-info/METADATA
verahession-0.1.28.dist-info/WHEEL
verahession-0.1.28.dist-info/top_level.txt
verahession-0.1.28.dist-info/RECORD
