Metadata-Version: 2.1
Name: verahession
Version: 0.1.28
Summary: Python client library for Vera AI chatbot by Hession Dynamics
Home-page: https://github.com/hession-dynamics/verahession
Author: Jack Hession
Author-email: support@hessiondynamics.com
License: MIT
Platform: UNKNOWN
Classifier: Programming Language :: Python :: 3
Classifier: Operating System :: OS Independent
Classifier: License :: OSI Approved :: MIT License
Requires-Python: >=3.6
Requires-Dist: requests (>=2.20.0)
